casino_persistent/__init__.py
casino_persistent/base_entity.py
casino_persistent/consecutive_panel.py
casino_persistent/game.py
casino_persistent/panel.py
casino_persistent/payment.py
casino_persistent/room.py
casino_persistent/user.py
casino_persistent/wallet.py
casino_persistent/zone.py
casino_persistent/exceptions/__init__.py
casino_persistent/exceptions/api_errors.py
casino_persistent/utils/__init__.py
casino_persistent/utils/balance.py
casino_persistent/utils/crypto.py
casino_persistent/utils/price.py
casino_persistent/utils/shatoshi_parser.py
casino_persistent/utils/status.py
casino_persistent/utils/transaction_type.py
casino_persistent/utils/transfer_status.py
casino_persistent-1.0.8.dist-info/METADATA
casino_persistent-1.0.8.dist-info/RECORD
casino_persistent-1.0.8.dist-info/WHEEL
casino_persistent-1.0.8.dist-info/top_level.txt
