Metadata-Version: 2.1
Name: casino-persistent
Version: 1.0.8
Summary: Casino Persistent
Home-page: https://github.com/htrongnam/casino_persistent
Author: Nam Hoang
Author-email: namhoang@vncdevs.io
License: UNKNOWN
Platform: UNKNOWN
Classifier: Programming Language :: Python :: 3
Classifier: License :: OSI Approved :: MIT License
Classifier: Operating System :: OS Independent
Requires-Dist: SQLAlchemy
Requires-Dist: SQLAlchemy-Utils
Requires-Dist: Flask-SQLAlchemy
